setup.cfg
setup.py
CmdDict.egg-info/PKG-INFO
CmdDict.egg-info/SOURCES.txt
CmdDict.egg-info/dependency_links.txt
CmdDict.egg-info/entry_points.txt
CmdDict.egg-info/not-zip-safe
CmdDict.egg-info/top_level.txt
cmddict/__init__.py