Metadata-Version: 1.0
Name: CmdDict
Version: 1.0dev
Summary: A command line dictionary
Home-page: http://said.ozcan.co
Author: Said Ozcan
Author-email: said@ozcan.co
License: UNKNOWN
Keywords: dictionary command-line
Platform: UNKNOWN
